godel/__init__.py
godel/api.py
godel/fragments/EntityDetail.py
godel/fragments/EntityLink.py
godel/fragments/EntitySummary.py
godel/fragments/EnumConstraint.py
godel/fragments/PredicateDetails.py
godel/fragments/TripleWidget.py
godel/fragments/__init__.py
godel/models.py
godel/queries/AddTripleToEntityById.py
godel/queries/AdminTemplates.py
godel/queries/AssignValidation.py
godel/queries/Authenticate.py
godel/queries/Bounties.py
godel/queries/CreateEntity.py
godel/queries/CreateStatement.py
godel/queries/CreateTripleFlag.py
godel/queries/CreateUserFlag.py
godel/queries/CreateUserReport.py
godel/queries/CreateValidation.py
godel/queries/CurrentUserBlockchainData.py
godel/queries/CurrentUserContributions.py
godel/queries/CurrentUserLedgerRecords.py
godel/queries/CurrentUserValidationActivity.py
godel/queries/CurrentUserValidations.py
godel/queries/DeprecatedGetTripleForValidation.py
godel/queries/EntityByName.py
godel/queries/EntityContributors.py
godel/queries/EntityDetail.py
godel/queries/EntityGolden.py
godel/queries/EntityGoldenRedirect.py
godel/queries/EntityHistoryFeed.py
godel/queries/EntityIndex.py
godel/queries/EntitySearch.py
godel/queries/EntityType.py
godel/queries/FulfillTripleRequest.py
godel/queries/GetAuthenticationMessage.py
godel/queries/GetBounty.py
godel/queries/GetCitations.py
godel/queries/GetCurrentUser.py
godel/queries/GetEntities.py
godel/queries/GetPendingTripleRequest.py
godel/queries/GetTripleForValidation.py
godel/queries/GetUser.py
godel/queries/Leaderboard.py
godel/queries/LiveView.py
godel/queries/Predicate.py
godel/queries/PredicateDetail.py
godel/queries/PredicatesIPFS.py
godel/queries/ProfileIndex.py
godel/queries/ProtocolSchema.py
godel/queries/StatementDetails.py
godel/queries/StatementValidations.py
godel/queries/Templates.py
godel/queries/TripleCount.py
godel/queries/TripleEvent.py
godel/queries/UserContributions.py
godel/queries/UserNftRequests.py
godel/queries/UserVerifications.py
godel/queries/WalletIndex.py
godel-0.8.0.dist-info/LICENSE
godel-0.8.0.dist-info/WHEEL
godel-0.8.0.dist-info/METADATA
godel-0.8.0.dist-info/RECORD
