Metadata-Version: 2.1
Name: godel
Version: 0.8.0
Summary: Golden's Python SDK for its Protocol: Decentralized Canonical Knowledge Graph
Author: aychang95
Requires-Python: >=3.7.10,<3.11
Classifier: Programming Language :: Python :: 3
Classifier: Programming Language :: Python :: 3.10
Classifier: Programming Language :: Python :: 3.8
Classifier: Programming Language :: Python :: 3.9
Provides-Extra: data-tools
Provides-Extra: docs
Provides-Extra: web3
Requires-Dist: Faker (>=15.3.1,<16.0.0)
Requires-Dist: ipywidgets (>=7.6.3,<8.0.0); extra == "data-tools"
Requires-Dist: jupyterlab (>=3.0.0,<4.0.0); extra == "data-tools"
Requires-Dist: mkdocs (>=1.3.0,<2.0.0)
Requires-Dist: mkdocs-jupyter (>=0.20.1,<0.21.0); extra == "docs"
Requires-Dist: mkdocs-material (>=8.2.9,<9.0.0); extra == "docs"
Requires-Dist: mkdocstrings[python] (>=0.19.0,<0.20.0); extra == "docs"
Requires-Dist: numpy (==1.21.6); extra == "data-tools"
Requires-Dist: pandas (==1.3.5); extra == "data-tools"
Requires-Dist: requests (>=2.27.1,<3.0.0)
Requires-Dist: setuptools (>=65.6.3,<66.0.0)
Requires-Dist: sgqlc (>=16.0,<17.0)
Requires-Dist: tqdm (>=4.63.1,<5.0.0)
Requires-Dist: web3 (>=5.28.0,<6.0.0); extra == "web3"
Requires-Dist: wheel (>=0.36.2,<0.37.0)
